airflow/providers/papermill/__init__.py
airflow/providers/papermill/get_provider_info.py
airflow/providers/papermill/version_compat.py
airflow/providers/papermill/hooks/__init__.py
airflow/providers/papermill/hooks/kernel.py
airflow/providers/papermill/operators/__init__.py
airflow/providers/papermill/operators/papermill.py
apache_airflow_providers_papermill-3.12.1.dist-info/entry_points.txt
apache_airflow_providers_papermill-3.12.1.dist-info/licenses/LICENSE
apache_airflow_providers_papermill-3.12.1.dist-info/licenses/NOTICE
apache_airflow_providers_papermill-3.12.1.dist-info/WHEEL
apache_airflow_providers_papermill-3.12.1.dist-info/METADATA
apache_airflow_providers_papermill-3.12.1.dist-info/RECORD
